neosv/__init__.py
neosv/annotation_class.py
neosv/annotation_utils.py
neosv/args.py
neosv/fusion_class.py
neosv/fusion_utils.py
neosv/input.py
neosv/main.py
neosv/netMHC.py
neosv/output.py
neosv/result_filter.py
neosv/sequence_utils.py
neosv/sv_class.py
neosv/sv_utils.py
neosv/transcript_utils.py
neosv-0.0.4.dist-info/METADATA
neosv-0.0.4.dist-info/WHEEL
neosv-0.0.4.dist-info/entry_points.txt
neosv-0.0.4.dist-info/top_level.txt
neosv-0.0.4.dist-info/RECORD
